logodetect/__init__.py
logodetect/augmenters.py
logodetect/cli.py
logodetect/constants.py
logodetect/recognizer.py
logodetect/utils.py
logodetect/classifiers/__init__.py
logodetect/classifiers/knn.py
logodetect/classifiers/siamese.py
logodetect/detectors/__init__.py
logodetect/detectors/faster_rcnn.py
logodetect-1.1.3.dist-info/LICENSE
logodetect-1.1.3.dist-info/METADATA
logodetect-1.1.3.dist-info/WHEEL
logodetect-1.1.3.dist-info/entry_points.txt
logodetect-1.1.3.dist-info/top_level.txt
logodetect-1.1.3.dist-info/RECORD
