Metadata-Version: 2.1
Name: logodetect
Version: 1.1.3
Summary: One-shot logo detection for videos and images.
Home-page: https://github.com/Heldenkombinat/logodetect
Author: Jorge Davila Chacon
Author-email: jorge@heldenkombinat.com
License: GNU AGPLv3
Download-URL: https://github.com/Heldenkombinat/logodetect/tarball/1.1.0
Platform: UNKNOWN
Classifier: Development Status :: 4 - Beta
Classifier: Intended Audience :: Developers
Classifier: Environment :: Console
Classifier: Operating System :: POSIX :: Linux
Classifier: Programming Language :: Python :: 3
License-File: LICENSE
Requires-Dist: click (>=7.1.1)
Requires-Dist: Cython (>=0.29.15)
Requires-Dist: Flask (>=1.1.1)
Requires-Dist: Flask-Cors (>=3.0.9)
Requires-Dist: gunicorn (>=20.0.4)
Requires-Dist: imgaug (>=0.4.0)
Requires-Dist: jupyterlab (==3.2.4)
Requires-Dist: matplotlib (>=2.2.5)
Requires-Dist: moviepy (>=1.0.1)
Requires-Dist: numpy (>=1.18.2)
Requires-Dist: opencv-python (>=4.2.0.32)
Requires-Dist: pandas (>=1.0.3)
Requires-Dist: pytest (>=6.2.4)
Requires-Dist: scikit-image (>=0.16.2)
Requires-Dist: scikit-learn (>=0.22.1)
Requires-Dist: scipy (>=1.4.1)
Requires-Dist: torch (>=1.9.0)
Requires-Dist: torchvision (>=0.10.0)
Requires-Dist: tqdm (>=4.42.1)
Provides-Extra: dev
Requires-Dist: black ; extra == 'dev'
Requires-Dist: pre-commit ; extra == 'dev'
Requires-Dist: flask ; extra == 'dev'
Requires-Dist: gunicorn ; extra == 'dev'
Provides-Extra: tests
Requires-Dist: pytest ; extra == 'tests'
Requires-Dist: pytest-pep8 ; extra == 'tests'
Requires-Dist: pytest-cov ; extra == 'tests'
Requires-Dist: mock ; extra == 'tests'
Requires-Dist: pylint ; extra == 'tests'
Requires-Dist: autopep8 ; extra == 'tests'
